archiver/__init__.py
archiver/archiver.py
archiver/cli.py
archiver/manager.py
archiver_zim-0.3.6.data/data/share/man/man1/archiver-zim-archive.1
archiver_zim-0.3.6.data/data/share/man/man1/archiver-zim-manage.1
archiver_zim-0.3.6.data/data/share/man/man1/archiver-zim.1
archiver_zim-0.3.6.dist-info/licenses/LICENSE
archiver_zim-0.3.6.dist-info/METADATA
archiver_zim-0.3.6.dist-info/WHEEL
archiver_zim-0.3.6.dist-info/entry_points.txt
archiver_zim-0.3.6.dist-info/top_level.txt
archiver_zim-0.3.6.dist-info/RECORD
