Metadata-Version: 2.4
Name: archiver-zim
Version: 0.3.6
Summary: A tool to download videos from various platforms and create ZIM archives
Home-page: https://github.com/Sudo-Ivan/archiver-zim
Author: Sudo-Ivan
Author-email: 
Classifier: Programming Language :: Python :: 3
Classifier: Programming Language :: Python :: 3.10
Classifier: Programming Language :: Python :: 3.11
Classifier: Programming Language :: Python :: 3.12
Classifier: Programming Language :: Python :: 3.13
Classifier: License :: OSI Approved :: MIT License
Classifier: Operating System :: OS Independent
Requires-Python: >=3.10,<3.14
License-File: LICENSE
Requires-Dist: yt-dlp>=2025.4.30
Requires-Dist: python-dateutil>=2.9.0.post0
Requires-Dist: click>=8.1.8
Requires-Dist: rich>=14.0.0
Requires-Dist: libzim>=3.7.0
Requires-Dist: feedparser>=6.0.11
Requires-Dist: requests>=2.32.3
Requires-Dist: pyyaml>=6.0.2
Dynamic: author
Dynamic: classifier
Dynamic: description
Dynamic: description-content-type
Dynamic: home-page
Dynamic: license-file
Dynamic: requires-dist
Dynamic: requires-python
Dynamic: summary
